h5nav/__init__.py
h5nav/cli.py
h5nav-0.1.7.dist-info/METADATA
h5nav-0.1.7.dist-info/WHEEL
h5nav-0.1.7.dist-info/entry_points.txt
h5nav-0.1.7.dist-info/licenses/LICENSE
h5nav-0.1.7.dist-info/RECORD
