Metadata-Version: 2.4
Name: h5nav
Version: 0.1.7
Summary: hdf5 file interactive navigation and editing tool
Project-URL: Homepage, https://github.com/clapeyre/h5nav
Author-email: "Corentin J. Lapeyre" <corentin.lapeyre@gmail.com>
License: MIT License
License-File: LICENSE
Classifier: Development Status :: 4 - Beta
Classifier: License :: OSI Approved :: MIT License
Classifier: Programming Language :: Python :: 3
Requires-Python: >=3.9
Requires-Dist: h5py>=2.5
Requires-Dist: numpy>=1.10
Provides-Extra: dev
Requires-Dist: pytest; extra == 'dev'
Requires-Dist: pytest-cov; extra == 'dev'
